
/**
 * Byte code enumeration
 * Autogenerated. DO NOT EDIT!
 */
typedef enum PmBcode_e
{

	STOP_CODE = 0, /* 0x0 */
	POP_TOP = 1, /* 0x1 */
	ROT_TWO = 2, /* 0x2 */
	ROT_THREE = 3, /* 0x3 */
	DUP_TOP = 4, /* 0x4 */
	ROT_FOUR = 5, /* 0x5 */
	POP_TOP_RAISE_IF_FALSE = 6, /* 0x6 */
	SHOUT = 8, /* 0x8 */
	NOP = 9, /* 0x9 */
	UNARY_POSITIVE = 10, /* 0xa */
	UNARY_NEGATIVE = 11, /* 0xb */
	UNARY_NOT = 12, /* 0xc */
	UNARY_CONVERT = 13, /* 0xd */
	UNARY_INVERT = 15, /* 0xf */
	BINARY_POWER = 19, /* 0x13 */
	BINARY_MULTIPLY = 20, /* 0x14 */
	BINARY_DIVIDE = 21, /* 0x15 */
	BINARY_MODULO = 22, /* 0x16 */
	BINARY_ADD = 23, /* 0x17 */
	BINARY_SUBTRACT = 24, /* 0x18 */
	BINARY_SUBSCR = 25, /* 0x19 */
	BINARY_FLOOR_DIVIDE = 26, /* 0x1a */
	BINARY_TRUE_DIVIDE = 27, /* 0x1b */
	INPLACE_FLOOR_DIVIDE = 28, /* 0x1c */
	INPLACE_TRUE_DIVIDE = 29, /* 0x1d */
	SLICE_0 = 30, /* 0x1e */
	SLICE_1 = 31, /* 0x1f */
	SLICE_2 = 32, /* 0x20 */
	SLICE_3 = 33, /* 0x21 */
	RECV_MSG = 34, /* 0x22 */
	DEFER_MSG = 35, /* 0x23 */
	UNDEFER_MSG = 36, /* 0x24 */
	STORE_SLICE_0 = 40, /* 0x28 */
	STORE_SLICE_1 = 41, /* 0x29 */
	STORE_SLICE_2 = 42, /* 0x2a */
	STORE_SLICE_3 = 43, /* 0x2b */
	DELETE_SLICE_0 = 50, /* 0x32 */
	DELETE_SLICE_1 = 51, /* 0x33 */
	DELETE_SLICE_2 = 52, /* 0x34 */
	DELETE_SLICE_3 = 53, /* 0x35 */
	STORE_MAP = 54, /* 0x36 */
	INPLACE_ADD = 55, /* 0x37 */
	INPLACE_SUBTRACT = 56, /* 0x38 */
	INPLACE_MULTIPLY = 57, /* 0x39 */
	INPLACE_DIVIDE = 58, /* 0x3a */
	INPLACE_MODULO = 59, /* 0x3b */
	STORE_SUBSCR = 60, /* 0x3c */
	DELETE_SUBSCR = 61, /* 0x3d */
	BINARY_LSHIFT = 62, /* 0x3e */
	BINARY_RSHIFT = 63, /* 0x3f */
	BINARY_AND = 64, /* 0x40 */
	BINARY_XOR = 65, /* 0x41 */
	BINARY_OR = 66, /* 0x42 */
	INPLACE_POWER = 67, /* 0x43 */
	GET_ITER = 68, /* 0x44 */
	PRINT_EXPR = 70, /* 0x46 */
	PRINT_ITEM = 71, /* 0x47 */
	PRINT_NEWLINE = 72, /* 0x48 */
	PRINT_ITEM_TO = 73, /* 0x49 */
	PRINT_NEWLINE_TO = 74, /* 0x4a */
	INPLACE_LSHIFT = 75, /* 0x4b */
	INPLACE_RSHIFT = 76, /* 0x4c */
	INPLACE_AND = 77, /* 0x4d */
	INPLACE_XOR = 78, /* 0x4e */
	INPLACE_OR = 79, /* 0x4f */
	BREAK_LOOP = 80, /* 0x50 */
	WITH_CLEANUP = 81, /* 0x51 */
	LOAD_LOCALS = 82, /* 0x52 */
	RETURN_VALUE = 83, /* 0x53 */
	IMPORT_STAR = 84, /* 0x54 */
	EXEC_STMT = 85, /* 0x55 */
	YIELD_VALUE = 86, /* 0x56 */
	POP_BLOCK = 87, /* 0x57 */
	END_FINALLY = 88, /* 0x58 */
	BUILD_CLASS = 89, /* 0x59 */
	STORE_NAME = 90, /* 0x5a */
	DELETE_NAME = 91, /* 0x5b */
	UNPACK_SEQUENCE = 92, /* 0x5c */
	FOR_ITER = 93, /* 0x5d */
	LIST_APPEND = 94, /* 0x5e */
	STORE_ATTR = 95, /* 0x5f */
	DELETE_ATTR = 96, /* 0x60 */
	STORE_GLOBAL = 97, /* 0x61 */
	DELETE_GLOBAL = 98, /* 0x62 */
	DUP_TOPX = 99, /* 0x63 */
	LOAD_CONST = 100, /* 0x64 */
	LOAD_NAME = 101, /* 0x65 */
	BUILD_TUPLE = 102, /* 0x66 */
	BUILD_LIST = 103, /* 0x67 */
	BUILD_SET = 104, /* 0x68 */
	BUILD_MAP = 105, /* 0x69 */
	LOAD_ATTR = 106, /* 0x6a */
	COMPARE_OP = 107, /* 0x6b */
	IMPORT_NAME = 108, /* 0x6c */
	IMPORT_FROM = 109, /* 0x6d */
	JUMP_FORWARD = 110, /* 0x6e */
	JUMP_IF_FALSE_OR_POP = 111, /* 0x6f */
	JUMP_IF_TRUE_OR_POP = 112, /* 0x70 */
	JUMP_ABSOLUTE = 113, /* 0x71 */
	POP_JUMP_IF_FALSE = 114, /* 0x72 */
	POP_JUMP_IF_TRUE = 115, /* 0x73 */
	LOAD_GLOBAL = 116, /* 0x74 */
	CONTINUE_LOOP = 119, /* 0x77 */
	SETUP_LOOP = 120, /* 0x78 */
	SETUP_EXCEPT = 121, /* 0x79 */
	SETUP_FINALLY = 122, /* 0x7a */
	LOAD_FAST = 124, /* 0x7c */
	STORE_FAST = 125, /* 0x7d */
	DELETE_FAST = 126, /* 0x7e */
	RAISE_VARARGS = 130, /* 0x82 */
	CALL_FUNCTION = 131, /* 0x83 */
	MAKE_FUNCTION = 132, /* 0x84 */
	BUILD_SLICE = 133, /* 0x85 */
	MAKE_CLOSURE = 134, /* 0x86 */
	LOAD_CLOSURE = 135, /* 0x87 */
	LOAD_DEREF = 136, /* 0x88 */
	STORE_DEREF = 137, /* 0x89 */
	TAIL_CALL_FUNCTION = 138, /* 0x8a */
	CALL_FUNCTION_VAR = 140, /* 0x8c */
	CALL_FUNCTION_KW = 141, /* 0x8d */
	CALL_FUNCTION_VAR_KW = 142, /* 0x8e */
	SETUP_WITH = 143, /* 0x8f */
	EXTENDED_ARG = 145, /* 0x91 */
	SET_ADD = 146, /* 0x92 */
	MAP_ADD = 147, /* 0x93 */
	LOAD_UNBOUND_NAME = 150, /* 0x96 */
	LOAD_UNBOUND_GLOBAL = 151, /* 0x97 */
	LOAD_UNBOUND_FAST = 152, /* 0x98 */

} PmBcode_t, *pPmBcode_t;

